[
  {
    "type":"SINGLE_DISPLAY_LEFT",
    "singleDisplayLeftTitle":"配管类型：",
    "singleDisplayLeftContent":"钢管"
  },
  {
    "type":"SINGLE_DISPLAY_LEFT",
    "singleDisplayLeftTitle":"规格型号：",
    "singleDisplayLeftContent":"888m"
  },
  {
    "type":"SINGLE_DISPLAY_LEFT",
    "singleDisplayLeftTitle":"单孔长度：",
    "singleDisplayLeftContent":"888m"
  },
  {
    "type":"SINGLE_DISPLAY_LEFT",
    "singleDisplayLeftTitle":"孔数：",
    "singleDisplayLeftContent":"888孔"
  },
  {
    "type":"SINGLE_DISPLAY_LEFT",
    "singleDisplayLeftTitle":"混凝土包封：",
    "singleDisplayLeftContent":"888m³"
  },
  {
    "type":"SINGLE_DISPLAY_LEFT",
    "singleDisplayLeftTitle":"长：",
    "singleDisplayLeftContent":"8m"
  },
  {
    "type":"SINGLE_DISPLAY_LEFT",
    "singleDisplayLeftTitle":"深：",
    "singleDisplayLeftContent":"m"
  },
  {
    "type":"SHIFT_INPUT",
    "shiftInputTitle":"照片上传",
    "necessary":false
  }
]