[
  {
    "type":"SINGLE_DISPLAY_RIGHT",
    "singleDisplayRightTitle":"需求类别",
    "singleDisplayRightContent":"",
    "key":"requirementVariety",
    "sendFormat": "String"
  },
  {
    "type":"SINGLE_DISPLAY_RIGHT",
    "singleDisplayRightTitle":"三方服务清册",
    "singleDisplayRightContent":"  录入  ",
    "key": "thirdLists",
    "sendFormat": "JsonArray"
  },
  {
    "type":"SELECT_DIALOG",
    "selectTitle":"合作方属性",
    "selectOption1Items":["单位","个人"],
    "key":"partnerAttribute",
    "sendFormat":"Long"
  },
  {
    "type":"SELECT_DIALOG",
    "selectTitle":"费用标准",
    "selectOption1Items":["面议","按清单报价"],
    "key":"fareStandard",
    "sendFormat":"Long"
  },
  {
    "type":"SINGLE_DISPLAY_RIGHT",
    "singleDisplayRightTitle":"联系人",
    "singleDisplayRightContent":" ",
    "key":"name",
    "sendFormat":"String"
  },
  {
    "type":"SINGLE_DISPLAY_RIGHT",
    "singleDisplayRightTitle":"联系电话",
    "singleDisplayRightContent":" ",
    "key":"phone",
    "sendFormat":"String"
  },
  {
    "type":"INPUT_WITH_UNIT",
    "inputUnitTitle":"发布有效期",
    "inputUnit":"(天)",
    "key":"validTime",
    "sendFormat":"Long"
  },
  {
    "type": "HINT",
    "hintContent": "注:字符前有*为必填。",
    "customFontColor":"#FFFF0000",
    "startPosition":6,
    "endPosition":7
  },
  {
    "type":"INPUT_WITH_TEXTAREA",
    "textAreaTitle":"附加信息",
    "textAreaContent":"有不良记录者请勿联系",
    "necessary": true,
    "hint": "有不良记录者请勿联系",
    "key":"additionalExplain",
    "sendFormat":"String"
  }
]