[
  {
    "type": "SINGLE_DISPLAY_RIGHT",
    "singleDisplayRightTitle": "发布类别",
    "singleDisplayRightContent": "跨越架施工队"
  },
  {
    "type":"MULTI_BUTTON",
    "buttonTitle":"成员清册",
    "buttonName":["在线编辑"],
    "additionalKey":"provideCrewListsFile"
  },
  {
    "type":"MULTI_BUTTON",
    "buttonTitle":"车辆",
    "buttonName":["在线编辑"]
  },
  {
    "type":"MULTI_BUTTON",
    "buttonTitle":"工器具清册",
    "buttonName":["在线编辑"],
    "additionalKey": "constructionToolListFile"
  },
  {
    "type": "SINGLE_DISPLAY_RIGHT",
    "singleDisplayRightTitle": "负责人所在地",
    "singleDisplayRightContent": ""
  },

  {
    "type": "SINGLE_DISPLAY_RIGHT",
    "singleDisplayRightTitle": "负责人",
    "singleDisplayRightContent": "xxx"
  },
  {
    "type": "SINGLE_DISPLAY_RIGHT",
    "singleDisplayRightTitle": "负责人电话",
    "singleDisplayRightContent": "xxx"
  },
  {
    "type":"INPUT_WITH_UNIT",
    "inputUnitTitle":"有效期",
    "inputUnit":"(天)",
    "key":"validTime",
    "sendFormat": "Int"
  },
  {
    "type":"HINT",
    "hintContent":"注:字符前有 * 为必填。",
    "customFontColor": "#FF0000",
    "startPosition": "6",
    "endPosition": "8"
  }
]